CONTRIBUTORS.txt
Changelog
LICENSE
MANIFEST.in
README.rst
TODO
setup.cfg
setup.py
distll_celery/__init__.py
distll_celery/__main__.py
distll_celery/_state.py
distll_celery/beat.py
distll_celery/bootsteps.py
distll_celery/canvas.py
distll_celery/exceptions.py
distll_celery/five.py
distll_celery/local.py
distll_celery/platforms.py
distll_celery/result.py
distll_celery/schedules.py
distll_celery/signals.py
distll_celery/states.py
distll_celery.egg-info/PKG-INFO
distll_celery.egg-info/SOURCES.txt
distll_celery.egg-info/dependency_links.txt
distll_celery.egg-info/entry_points.txt
distll_celery.egg-info/not-zip-safe
distll_celery.egg-info/requires.txt
distll_celery.egg-info/top_level.txt
distll_celery/app/__init__.py
distll_celery/app/amqp.py
distll_celery/app/annotations.py
distll_celery/app/backends.py
distll_celery/app/base.py
distll_celery/app/builtins.py
distll_celery/app/control.py
distll_celery/app/defaults.py
distll_celery/app/events.py
distll_celery/app/log.py
distll_celery/app/registry.py
distll_celery/app/routes.py
distll_celery/app/task.py
distll_celery/app/trace.py
distll_celery/app/utils.py
distll_celery/apps/__init__.py
distll_celery/apps/beat.py
distll_celery/apps/multi.py
distll_celery/apps/worker.py
distll_celery/backends/__init__.py
distll_celery/backends/amqp.py
distll_celery/backends/async.py
distll_celery/backends/base.py
distll_celery/backends/cache.py
distll_celery/backends/cassandra.py
distll_celery/backends/consul.py
distll_celery/backends/couchbase.py
distll_celery/backends/couchdb.py
distll_celery/backends/elasticsearch.py
distll_celery/backends/filesystem.py
distll_celery/backends/mongodb.py
distll_celery/backends/redis.py
distll_celery/backends/riak.py
distll_celery/backends/rpc.py
distll_celery/backends/database/__init__.py
distll_celery/backends/database/models.py
distll_celery/backends/database/session.py
distll_celery/bin/__init__.py
distll_celery/bin/amqp.py
distll_celery/bin/base.py
distll_celery/bin/beat.py
distll_celery/bin/call.py
distll_celery/bin/celery.py
distll_celery/bin/celeryd_detach.py
distll_celery/bin/control.py
distll_celery/bin/events.py
distll_celery/bin/graph.py
distll_celery/bin/list.py
distll_celery/bin/logtool.py
distll_celery/bin/migrate.py
distll_celery/bin/multi.py
